awslabs/__init__.py
awslabs/billing_cost_management_mcp_server/__init__.py
awslabs/billing_cost_management_mcp_server/models.py
awslabs/billing_cost_management_mcp_server/server.py
awslabs/billing_cost_management_mcp_server/prompts/README.md
awslabs/billing_cost_management_mcp_server/prompts/__init__.py
awslabs/billing_cost_management_mcp_server/prompts/decorator.py
awslabs/billing_cost_management_mcp_server/prompts/graviton_migration.py
awslabs/billing_cost_management_mcp_server/prompts/savings_plans.py
awslabs/billing_cost_management_mcp_server/prompts/types.py
awslabs/billing_cost_management_mcp_server/templates/recommendation_templates/ebs_volume.template
awslabs/billing_cost_management_mcp_server/templates/recommendation_templates/ec2_asg.template
awslabs/billing_cost_management_mcp_server/templates/recommendation_templates/ec2_instance.template
awslabs/billing_cost_management_mcp_server/templates/recommendation_templates/ecs_service.template
awslabs/billing_cost_management_mcp_server/templates/recommendation_templates/idle.template
awslabs/billing_cost_management_mcp_server/templates/recommendation_templates/lambda_function.template
awslabs/billing_cost_management_mcp_server/templates/recommendation_templates/rds_database.template
awslabs/billing_cost_management_mcp_server/templates/recommendation_templates/reserved_instances.template
awslabs/billing_cost_management_mcp_server/templates/recommendation_templates/savings_plans.template
awslabs/billing_cost_management_mcp_server/tools/__init__.py
awslabs/billing_cost_management_mcp_server/tools/aws_pricing_operations.py
awslabs/billing_cost_management_mcp_server/tools/aws_pricing_tools.py
awslabs/billing_cost_management_mcp_server/tools/bcm_pricing_calculator_tools.py
awslabs/billing_cost_management_mcp_server/tools/budget_tools.py
awslabs/billing_cost_management_mcp_server/tools/compute_optimizer_tools.py
awslabs/billing_cost_management_mcp_server/tools/cost_anomaly_tools.py
awslabs_billing_cost_management_mcp_server-0.0.12.dist-info/METADATA
awslabs_billing_cost_management_mcp_server-0.0.12.dist-info/WHEEL
awslabs_billing_cost_management_mcp_server-0.0.12.dist-info/entry_points.txt
awslabs_billing_cost_management_mcp_server-0.0.12.dist-info/licenses/LICENSE
awslabs_billing_cost_management_mcp_server-0.0.12.dist-info/licenses/NOTICE
awslabs_billing_cost_management_mcp_server-0.0.12.dist-info/RECORD
