Metadata-Version: 2.4
Name: awslabs.billing-cost-management-mcp-server
Version: 0.0.12
Summary: A Model Context Protocol (MCP) server that provides tools for AWS Billing and Cost Management by wrapping boto3 SDK functions.
Project-URL: homepage, https://awslabs.github.io/mcp/
Project-URL: docs, https://awslabs.github.io/mcp/servers/billing-cost-management-mcp-server/
Project-URL: documentation, https://awslabs.github.io/mcp/servers/billing-cost-management-mcp-server/
Project-URL: repository, https://github.com/awslabs/mcp.git
Project-URL: changelog, https://github.com/awslabs/mcp/blob/main/src/billing-cost-management-mcp-server/CHANGELOG.md
Author: Amazon Web Services
Author-email: AWSLabs MCP <203918161+awslabs-mcp@users.noreply.github.com>, Rams Sundaram <shsrams@amazon.com>
License: Apache-2.0
License-File: LICENSE
License-File: NOTICE
Classifier: License :: OSI Approved :: Apache Software License
Classifier: Operating System :: OS Independent
Classifier: Programming Language :: Python
Classifier: Programming Language :: Python :: 3
Classifier: Programming Language :: Python :: 3.10
Classifier: Programming Language :: Python :: 3.11
Classifier: Programming Language :: Python :: 3.12
Classifier: Programming Language :: Python :: 3.13
Requires-Python: >=3.10
Requires-Dist: boto3>=1.34.0
Requires-Dist: fastmcp>=2.14.0
Requires-Dist: loguru>=0.7.0
Requires-Dist: mcp[cli]>=1.23.0
Requires-Dist: pydantic>=2.10.6
Requires-Dist: python-dotenv>=1.0.0
